redesBayesianas_18364_18761/__init__.py
redesBayesianas_18364_18761/redes.py
RedesBayesianas_18364_18761-0.0.3.dist-info/METADATA
RedesBayesianas_18364_18761-0.0.3.dist-info/WHEEL
RedesBayesianas_18364_18761-0.0.3.dist-info/top_level.txt
RedesBayesianas_18364_18761-0.0.3.dist-info/RECORD
