Metadata-Version: 2.1
Name: RedesBayesianas-18364-18761
Version: 0.0.3
Summary: Libreria de Redes Bayesianas
Home-page: UNKNOWN
Author: Jorge Perez y Diego Ruiz
Author-email: <per18364@uvg.edu.gt>
License: UNKNOWN
Keywords: python,bayes,bayesian network
Platform: UNKNOWN
Classifier: Development Status :: 1 - Planning
Classifier: Intended Audience :: Developers
Classifier: Programming Language :: Python :: 3
Classifier: Operating System :: Unix
Classifier: Operating System :: MacOS :: MacOS X
Classifier: Operating System :: Microsoft :: Windows
Requires-Dist: numpy
Requires-Dist: pyAgrum
